{
  "id": "money_w02",
  "meta": {
    "track": "money",
    "theme": "お金の基礎（2/4）｜行動バイアス・保険・積立設計",
    "arc": "お金入門（全4週）",
    "weekIndex": 2,
    "arcTotal": 4
  },
  "cards": [
    {
      "type": "mcq",
      "q": "損失回避バイアスとは何か？",
      "choices": [
        "利益を過大評価する",
        "損失の痛みを利益の喜びより強く感じる",
        "短期的な利益を優先する",
        "確率を正しく計算できない"
      ],
      "answerIndex": 1,
      "explain": "同額でも損失の心理的影響は利益の約2倍強い。"
    },
    {
      "type": "mcq",
      "q": "アンカリング効果の投資への影響は？",
      "choices": [
        "最初に見た価格に引きずられる",
        "分散投資が進む",
        "リスクを正確に評価できる",
        "長期投資が増える"
      ],
      "answerIndex": 0,
      "explain": "初期の参照点が判断の基準となり適切な評価を妨げる。"
    },
    {
      "type": "mcq",
      "q": "サンクコストの誤謬を避けるには？",
      "choices": [
        "過去の投資額を重視する",
        "今後の期待値で判断する",
        "感情的に執着する",
        "他人の意見に従う"
      ],
      "answerIndex": 1,
      "explain": "既に使った費用は戻らない。将来の価値で判断する。"
    },
    {
      "type": "mcq",
      "q": "医療保険の本質的な役割は？",
      "choices": [
        "医療費を安くする",
        "健康を維持する",
        "高額医療費のリスクヘッジ",
        "税金を減らす"
      ],
      "answerIndex": 2,
      "explain": "低頻度だが家計破綻レベルの医療費に備える。"
    },
    {
      "type": "mcq",
      "q": "掛け捨て保険のメリットは？",
      "choices": [
        "貯蓄性がある",
        "保険料が安い",
        "必ず戻ってくる",
        "投資効果が高い"
      ],
      "answerIndex": 1,
      "explain": "保障に特化し貯蓄機能がない分、保険料を抑えられる。"
    },
    {
      "type": "mcq",
      "q": "積立投資のドルコスト平均法の効果は？",
      "choices": [
        "必ず利益が出る",
        "購入単価を平準化",
        "最高値で買える",
        "手数料が無料になる"
      ],
      "answerIndex": 1,
      "explain": "定期定額購入で高い時は少なく安い時は多く買える。"
    },
    {
      "type": "mcq",
      "q": "確証バイアスが投資判断に与える影響は？",
      "choices": [
        "反対意見も積極的に検討する",
        "自分の考えを支持する情報ばかり集める",
        "リスクを過小評価する",
        "分散投資が進む"
      ],
      "answerIndex": 1,
      "explain": "都合の良い情報だけを集め、偏った判断をしやすくなる。"
    },
    {
      "type": "mcq",
      "q": "生命保険の必要保障額の基本的な考え方は？",
      "choices": [
        "年収の10倍",
        "遺族の生活費－遺族年金等",
        "貯蓄額と同じ",
        "固定で1億円"
      ],
      "answerIndex": 1,
      "explain": "残された家族に必要な額から公的保障を引いた不足分。"
    },
    {
      "type": "mcq",
      "q": "積立NISAの年間上限額（2024年以降）は？",
      "choices": [
        "40万円",
        "80万円",
        "120万円",
        "240万円"
      ],
      "answerIndex": 2,
      "explain": "2024年から年間120万円に拡充された。"
    },
    {
      "type": "mcq",
      "q": "リバランスの主な目的は？",
      "choices": [
        "利益確定",
        "資産配分を元に戻す",
        "手数料を払う",
        "全て売却する"
      ],
      "answerIndex": 1,
      "explain": "価格変動で崩れた資産配分を当初の比率に調整する。"
    }
  ]
}
